README.md
pyproject.toml
setup.cfg
setup.py
spacetower_orbit_determination_python_client/__init__.py
spacetower_orbit_determination_python_client/api_client.py
spacetower_orbit_determination_python_client/api_response.py
spacetower_orbit_determination_python_client/configuration.py
spacetower_orbit_determination_python_client/exceptions.py
spacetower_orbit_determination_python_client/py.typed
spacetower_orbit_determination_python_client/rest.py
spacetower_orbit_determination_python_client.egg-info/PKG-INFO
spacetower_orbit_determination_python_client.egg-info/SOURCES.txt
spacetower_orbit_determination_python_client.egg-info/dependency_links.txt
spacetower_orbit_determination_python_client.egg-info/requires.txt
spacetower_orbit_determination_python_client.egg-info/top_level.txt
spacetower_orbit_determination_python_client/api/__init__.py
spacetower_orbit_determination_python_client/api/default_api.py
spacetower_orbit_determination_python_client/models/__init__.py
spacetower_orbit_determination_python_client/models/anomaly_type.py
spacetower_orbit_determination_python_client/models/apriori_residuals_computation_request.py
spacetower_orbit_determination_python_client/models/apriori_residuals_computation_result.py
spacetower_orbit_determination_python_client/models/atmosphere_model.py
spacetower_orbit_determination_python_client/models/atmosphere_type.py
spacetower_orbit_determination_python_client/models/atmospheric_drag_perturbation.py
spacetower_orbit_determination_python_client/models/attitude_based_finite_thrust_schedule.py
spacetower_orbit_determination_python_client/models/attitude_law.py
spacetower_orbit_determination_python_client/models/attitude_law_type.py
spacetower_orbit_determination_python_client/models/attitude_sequence.py
spacetower_orbit_determination_python_client/models/attitude_sequence_type.py
spacetower_orbit_determination_python_client/models/batch_least_squares_estimation_configuration.py
spacetower_orbit_determination_python_client/models/batch_least_squares_measurement_parameters_estimation_request.py
spacetower_orbit_determination_python_client/models/batch_least_squares_orbit_estimation_request.py
spacetower_orbit_determination_python_client/models/batch_least_squares_propagation_parameters_estimation_request.py
