Metadata-Version: 2.1
Name: spacetower_orbit_determination_python_client
Version: 1.6.1
Summary: Orbit Determination API
Home-page: 
Author: OpenAPI Generator community
Author-email: team@openapitools.org
License: Exotrail
Keywords: OpenAPI,OpenAPI-Generator,Orbit Determination API
Requires-Dist: urllib3<2.1.0,>=1.25.3
Requires-Dist: python-dateutil
Requires-Dist: pydantic>=2
Requires-Dist: typing-extensions>=4.7.1
